ankigammon/__init__.py
ankigammon/__main__.py
ankigammon/models.py
ankigammon/settings.py
ankigammon/analysis/__init__.py
ankigammon/analysis/move_score_matrix.py
ankigammon/analysis/score_matrix.py
ankigammon/anki/__init__.py
ankigammon/anki/ankiconnect.py
ankigammon/anki/apkg_exporter.py
ankigammon/anki/card_generator.py
ankigammon/anki/card_styles.py
ankigammon/anki/deck_utils.py
ankigammon/gui/__init__.py
ankigammon/gui/app.py
ankigammon/gui/format_detector.py
ankigammon/gui/main_window.py
ankigammon/gui/resources.py
ankigammon/gui/silent_messagebox.py
ankigammon/gui/update_checker.py
ankigammon/gui/dialogs/__init__.py
ankigammon/gui/dialogs/export_dialog.py
ankigammon/gui/dialogs/import_options_dialog.py
ankigammon/gui/dialogs/input_dialog.py
ankigammon/gui/dialogs/note_dialog.py
ankigammon/gui/dialogs/regenerate_dialog.py
ankigammon/gui/dialogs/settings_dialog.py
ankigammon/gui/dialogs/shortcuts_dialog.py
ankigammon/gui/dialogs/update_dialog.py
ankigammon/gui/resources/down-arrow.svg
ankigammon/gui/resources/icon.icns
ankigammon/gui/resources/icon.ico
ankigammon/gui/resources/icon.png
ankigammon/gui/resources/style.qss
ankigammon/gui/widgets/__init__.py
ankigammon/gui/widgets/position_list.py
ankigammon/gui/widgets/smart_input.py
ankigammon/parsers/__init__.py
ankigammon/parsers/gnubg_match_parser.py
ankigammon/parsers/gnubg_parser.py
ankigammon/parsers/sgf_parser.py
ankigammon/parsers/xg_binary_parser.py
ankigammon/parsers/xg_text_parser.py
ankigammon/renderer/__init__.py
ankigammon/renderer/animation_controller.py
ankigammon/renderer/animation_helper.py
ankigammon/renderer/color_schemes.py
ankigammon/renderer/svg_board_renderer.py
ankigammon/thirdparty/__init__.py
ankigammon/thirdparty/xgdatatools/__init__.py
ankigammon/thirdparty/xgdatatools/xgimport.py
ankigammon/thirdparty/xgdatatools/xgstruct.py
ankigammon/thirdparty/xgdatatools/xgutils.py
ankigammon/thirdparty/xgdatatools/xgzarc.py
ankigammon/utils/__init__.py
ankigammon/utils/gnubg_analyzer.py
ankigammon-1.3.0.dist-info/licenses/LICENSE
ankigammon-1.3.0.dist-info/METADATA
ankigammon-1.3.0.dist-info/WHEEL
ankigammon-1.3.0.dist-info/entry_points.txt
ankigammon-1.3.0.dist-info/top_level.txt
ankigammon-1.3.0.dist-info/RECORD
