Metadata-Version: 2.4
Name: ankigammon
Version: 1.3.0
Summary: Convert eXtreme Gammon backgammon analysis into Anki flashcards
Author-email: AnkiGammon Contributors <admin@ankigammon.com>
License-Expression: MIT
Project-URL: Homepage, https://github.com/Deinonychus999/AnkiGammon
Project-URL: Repository, https://github.com/Deinonychus999/AnkiGammon
Project-URL: Documentation, https://github.com/Deinonychus999/AnkiGammon#readme
Project-URL: Issues, https://github.com/Deinonychus999/AnkiGammon/issues
Keywords: anki,flashcards,backgammon,extreme-gammon,xg,learning,spaced-repetition
Classifier: Development Status :: 5 - Production/Stable
Classifier: Intended Audience :: End Users/Desktop
Classifier: Topic :: Games/Entertainment :: Board Games
Classifier: Programming Language :: Python :: 3
Classifier: Programming Language :: Python :: 3.8
Classifier: Programming Language :: Python :: 3.9
Classifier: Programming Language :: Python :: 3.10
Classifier: Programming Language :: Python :: 3.11
Classifier: Programming Language :: Python :: 3.12
Requires-Python: >=3.8
License-File: LICENSE
Requires-Dist: genanki>=0.13.0
Requires-Dist: requests>=2.31.0
Requires-Dist: striprtf>=0.0.26
Requires-Dist: PySide6>=6.6.0
Requires-Dist: PySide6-Addons>=6.6.0
Requires-Dist: qtawesome>=1.3.0
Requires-Dist: backports.zoneinfo; python_version < "3.9"
Provides-Extra: dev
Requires-Dist: pyinstaller>=6.0.0; extra == "dev"
Requires-Dist: pytest>=7.0.0; extra == "dev"
Requires-Dist: bump-my-version>=0.28.0; extra == "dev"
Dynamic: license-file
